Adafruit_MotorHAT-1.4.0.dist-info/RECORD
Adafruit_MotorHAT-1.4.0.dist-info/top_level.txt
Adafruit_MotorHAT-1.4.0.dist-info/WHEEL
Adafruit_MotorHAT-1.4.0.dist-info/DESCRIPTION.rst
Adafruit_MotorHAT-1.4.0.dist-info/dependency_links.txt
Adafruit_MotorHAT-1.4.0.dist-info/METADATA
Adafruit_MotorHAT-1.4.0.dist-info/metadata.json
Adafruit_MotorHAT/Adafruit_PWM_Servo_Driver.py
Adafruit_MotorHAT/__init__.py
Adafruit_MotorHAT/Adafruit_MotorHAT_Motors.py
