Metadata-Version: 1.0
Name: Adafruit-MotorHAT
Version: 1.4.0
Summary: Library for Adafruit Motor HAT
Home-page: https://github.com/adafruit/Adafruit_Python_MotorHAT/
Author: Limor Fried
Author-email: support@adafruit.com
License: MIT
Platform: UNKNOWN
